{
  "Dic": [
    {
      "meaning": "ယာဉ်ကြောပိတ်ဆို့မှု",
      "kr": "차가 막히다"
    },
    {
      "meaning": "အေးသည်",
      "kr": "차다/차갑다"
    },
    {
      "meaning": "ဘိုးဘွားစဉ်ဆက်အတွက် ရိုးရာဓလေ့ လုပ်ဆောင်သည်",
      "kr": "차례를 지내다"
    },
    {
      "meaning": "ဝတ်ဆင်သည်",
      "kr": "착용하다"
    },
    {
      "meaning": "ဗုဒ္ဓဘာသာ/ခရစ်ယာန် ဘာသာရေးသီချင်း သီဆိုသည်",
      "kr": "찬불가/성가를 부르다"
    },
    {
      "meaning": "ပွန်းပဲ့ဒဏ်ရာ ရသည်",
      "kr": "찰과상을 입다"
    },
    {
      "meaning": "တက်ရောက်သည်",
      "kr": "참석하다"
    },
    {
      "meaning": "ဂိုဒေါင်",
      "kr": "창고"
    },
    {
      "meaning": "ကောင်တာ",
      "kr": "창구"
    },
    {
      "meaning": "ပြတင်းပေါက်",
      "kr": "창문"
    },
    {
      "meaning": "ဟင်းသီးဟင်းရွက်",
      "kr": "채소"
    },
    {
      "meaning": "စာအုပ်",
      "kr": "책"
    },
    {
      "meaning": "စားပွဲ",
      "kr": "책상"
    },
    {
      "meaning": "စာဖတ်သည်",
      "kr": "책을 읽다"
    },
    {
      "meaning": "ယူဆောင်သည်",
      "kr": "챙기다"
    },
    {
      "meaning": "စွန့်ပစ်သည်/ဆောင်ရွက်သည်",
      "kr": "처리하다"
    },
    {
      "meaning": "ဆေးညွှန်းရေးသည်",
      "kr": "처방하다"
    },
    {
      "meaning": "ကက်သလစ်ဘာသာ",
      "kr": "천주교(가톨릭)"
    },
    {
      "meaning": "သံမဏိဘောင် အလုပ်",
      "kr": "철골 작업"
    },
    {
      "meaning": "အားဖြည့်သံချောင်း",
      "kr": "철근"
    },
    {
      "meaning": "အားဖြည့်သံချောင်း အလုပ်",
      "kr": "철근 작업"
    },
    {
      "meaning": "အားဖြည့်သံချောင်း တပ်ဆင်သည်",
      "kr": "철근을 조립하다"
    },
    {
      "meaning": "သန့်ရှင်းမှု ထိန်းသိမ်းသည်",
      "kr": "청결을 유지하다"
    },
    {
      "meaning": "ဘေလ်",
      "kr": "청구서"
    },
    {
      "meaning": "သန့်ရှင်းရေး ကိရိယာ",
      "kr": "청소 도구"
    },
    {
      "meaning": "ဖုန်စုပ်စက် သုံးသည်",
      "kr": "청소기를 돌리다"
    },
    {
      "meaning": "သန့်ရှင်းရေး လုပ်သည်",
      "kr": "청소를 하다"
    },
    {
      "meaning": "မင်္ဂလာဖိတ်စာ",
      "kr": "청첩장"
    },
    {
      "meaning": "ခွင့်ပြုထားသည့် နေထိုင်နိုင်သည့် ကာလ",
      "kr": "체류 가능 기간"
    },
    {
      "meaning": "နေထိုင်ခွင့် ကာလ",
      "kr": "체류 기간"
    },
    {
      "meaning": "နေထိုင်ခွင့် အဆင့်အတန်း",
      "kr": "체류 자격"
    },
    {
      "meaning": "နေထိုင်ခွင့် အဆင့်အတန်းဖြင့် ခွင့်မပြုသော လုပ်ဆောင်မှုများ",
      "kr": "체류 자격 외 활동"
    },
    {
      "meaning": "နေထိုင်မှု အထောက်အထား စာရွက်စာတမ်း",
      "kr": "체류지 입증 서류"
    },
    {
      "meaning": "နေထိုင်သည်",
      "kr": "체류하다"
    },
    {
      "meaning": "အားကစားပြိုင်ပွဲပွဲ",
      "kr": "체육대회"
    },
    {
      "meaning": "ချက်ကတ်",
      "kr": "체크카드"
    },
    {
      "meaning": "ဖိတ်ကြားခံရသည်",
      "kr": "초대를 받다"
    },
    {
      "meaning": "ဖိတ်ကြားသည်",
      "kr": "초대하다"
    },
    {
      "meaning": "ချောကလက်",
      "kr": "초콜릿"
    },
    {
      "meaning": "စုစုပေါင်း လုပ်ခ",
      "kr": "총액"
    },
    {
      "meaning": "အမြင့်ဆုံး အပူချိန်",
      "kr": "최고기온"
    },
    {
      "meaning": "အနိမ့်ဆုံး အပူချိန်",
      "kr": "최저기온"
    },
    {
      "meaning": "အနိမ့်ဆုံး လုပ်ခ",
      "kr": "최저임금"
    },
    {
      "meaning": "ပထမဆုံး",
      "kr": "최초"
    },
    {
      "meaning": "အမြင့်ကနေ ပြုတ်ကျသည်",
      "kr": "추락하다"
    },
    {
      "meaning": "နှင်ထုတ်ခံရသည်",
      "kr": "추방되다"
    },
    {
      "meaning": "ချူးဆော့ (ကိုရီးယား ကျေးဇူးတော်နေ့)",
      "kr": "추석"
    },
    {
      "meaning": "အကြံပြုသည်",
      "kr": "추천하다"
    },
    {
      "meaning": "ဘောလုံးအသင်း",
      "kr": "축구 동호회"
    },
    {
      "meaning": "ဘောလုံးကစားသည်",
      "kr": "축구하다"
    },
    {
      "meaning": "နွားတင်းကုပ်/ဝက်ခြံ",
      "kr": "축사"
    },
    {
      "meaning": "အသားနှင့် နို့ထွက်ပစ္စည်း လုပ်ငန်း",
      "kr": "축산업"
    },
    {
      "meaning": "မင်္ဂလာ လက်ဆောင်ငွေ",
      "kr": "축의금"
    },
    {
      "meaning": "ပွဲတော် သွားကြည့်သည်",
      "kr": "축제를 구경하다"
    },
    {
      "meaning": "ဂုဏ်ပြုသည်",
      "kr": "축하하다"
    },
    {
      "meaning": "ထုတ်ပေးသည်",
      "kr": "출고하다"
    },
    {
      "meaning": "ထွက်ခွာရန် စီစဉ်ထားကြောင်း အစီရင်ခံစာ",
      "kr": "출국 예정 신고서"
    },
    {
      "meaning": "အလုပ်ချိန် စတင်သည့်အချိန်",
      "kr": "출근 시간"
    },
    {
      "meaning": "ငွေထုတ်ယူသည်",
      "kr": "출금하다"
    },
    {
      "meaning": "ထွက်ခွာသည်",
      "kr": "출발하다"
    },
    {
      "meaning": "မီးဖွားခွင့်",
      "kr": "출산 휴가"
    },
    {
      "meaning": "ကျူးကျော်ဝင်ရောက်ခြင်း မပြုရ",
      "kr": "출입 금지"
    },
    {
      "meaning": "လူဝင်မှုကြီးကြပ်ရေး ဝန်ဆောင်မှုရုံး",
      "kr": "출입국 관리소"
    },
    {
      "meaning": "လူဝင်မှုကြီးကြပ်ရေးရုံး",
      "kr": "출입국관리사무소"
    },
    {
      "meaning": "ဝင်ရောက်ခြင်း မပြုရ",
      "kr": "출입금지"
    },
    {
      "meaning": "ဝင်ပေါက်/ထွက်ပေါက်",
      "kr": "출입문"
    },
    {
      "meaning": "အလုပ်သွား/ပြန်ချိန်",
      "kr": "출퇴근 시간"
    },
    {
      "meaning": "ကုန်ပစ္စည်း တင်ပို့သည်",
      "kr": "출하하다"
    },
    {
      "meaning": "အကကသည်",
      "kr": "춤을 추다"
    },
    {
      "meaning": "အေးသည်",
      "kr": "춥다"
    },
    {
      "meaning": "တိုက်မိသည်",
      "kr": "충돌하다"
    },
    {
      "meaning": "လုံလောက်သည်",
      "kr": "충분하다"
    },
    {
      "meaning": "အလုပ်အကိုင် လေ့ကျင့်ရေး သင်တန်း တက်သည်",
      "kr": "취업 교육을 받다"
    },
    {
      "meaning": "အလုပ်လုပ်သည့် ကာလ",
      "kr": "취업 기간"
    },
    {
      "meaning": "အလုပ်ကာလ တိုးချဲ့ရန် လျှောက်လွှာ",
      "kr": "취업 활동 기간 연장 신청서"
    },
    {
      "meaning": "ဝန်ထမ်း",
      "kr": "취업자"
    },
    {
      "meaning": "အလုပ်ရသည်",
      "kr": "취업하다"
    },
    {
      "meaning": "သွားဘက်ဆိုင်ရာ",
      "kr": "치과"
    },
    {
      "meaning": "ကုသသည်",
      "kr": "치료를 하다"
    },
    {
      "meaning": "ဆေးကုသစရိတ်",
      "kr": "치료비"
    },
    {
      "meaning": "စကတ်",
      "kr": "치마"
    },
    {
      "meaning": "ချီမက် (ကြက်ကြော်နှင့် ဘီယာ)",
      "kr": "치맥"
    },
    {
      "meaning": "သွားတိုက်ဆေး",
      "kr": "치약"
    },
    {
      "meaning": "ရှင်းလင်းသည်",
      "kr": "치우다"
    },
    {
      "meaning": "ကြက်ကြော်",
      "kr": "치킨"
    },
    {
      "meaning": "သူငယ်ချင်း",
      "kr": "친구"
    },
    {
      "meaning": "သူငယ်ချင်းနှင့် တွေ့သည်",
      "kr": "친구를 만나다"
    },
    {
      "meaning": "ကြင်နာသည်/ကောင်းသည်",
      "kr": "친절하다"
    },
    {
      "meaning": "ဆွေမျိုးအိမ် သွားသည်",
      "kr": "친척집에 가다"
    },
    {
      "meaning": "ရင်းနှီးလာသည်",
      "kr": "친해지다"
    },
    {
      "meaning": "အသက် ၇၀ ပြည့် မွေးနေ့",
      "kr": "칠순"
    },
    {
      "meaning": "ကျောက်သင်ပုန်း/ဘုတ်ပြား",
      "kr": "칠판"
    },
    {
      "meaning": "တံတွေး ထွေးသည်",
      "kr": "침을 뱉다"
    },
    {
      "meaning": "သွားတိုက်တံ",
      "kr": "칫솔"
    },
    {
      "meaning": "ချီးမွမ်းသည်",
      "kr": "칭찬하다"
    }
  ]
}