{
  "Dic" : [
   {
      "meaning" : "सवारी साधन आदि चढेर जानु",
      "kr" : "타고 가다"
    },
    {
      "meaning" : "सवारी साधन आदि चढेर आउनु",
      "kr" : "타고 오다"
    },
    {
      "meaning" : "चडनु",
      "kr" : "타다"
    },
    {
      "meaning" : "अस्ट्रीच",
      "kr" : "타조"
    },
    {
      "meaning" : "थाइल्याण्ड",
      "kr" : "태국"
    },
    {
      "meaning" : "तेक्वान्दो तालिम",
      "kr" : "태권도 교육"
    },
     {
      "meaning" : "डेलिभरी",
      "kr" : "택배"
    },
    {
      "meaning" : "ट्याक्सी",
      "kr" : "택시"
    },
    {
      "meaning" : "ट्याक्सी स्ट्याण्ड",
      "kr" : "택시 승강장"
    },
    {
      "meaning" : "टेनिस खेल्नु",
      "kr" : "테니스를 치다"
    },
    {
      "meaning" : "टेलिभिजन",
      "kr" : "텔레비전"
    },
    {
      "meaning" : "टेलिभिजन हेर्नु",
      "kr" : "텔레비전을 보다"
    },
    {
      "meaning" : "खरायो",
      "kr" : "토끼"
    },
     {
      "meaning" : "बान्ता गर्नु",
      "kr" : "토하다"
    },
    {
      "meaning" : "आरा",
      "kr" : "톱"
    },
    {
      "meaning" : "माछाको जाल",
      "kr" : "통발"
    },
    {
      "meaning" : "व्याख्या",
      "kr" : "통역"
    },
    {
      "meaning" : "बाहिरी रोगी उपचार प्रदान गर्नु",
      "kr" : "통원 치료를 하다"
    },
    {
      "meaning" : "बैंक बुक",
      "kr" : "통장"
    },
    {
      "meaning" : "बैंकबुक अपडेट",
      "kr" : "통장 정리"
    },
    {
      "meaning" : "बैंक खातामा जम्मा गर्नु",
      "kr" : "통장으로 들어가다"
    },
    {
      "meaning" : "लाइन व्यस्त हुनु",
      "kr" : "통화 중이다"
    },
    {
      "meaning" : "छुट्टि समय",
      "kr" : "퇴근 시간"
    },
    {
      "meaning" : "निवृत्तिभरण",
      "kr" : "퇴직금"
    },
    {
      "meaning" : "सेवानिवृत्त हुनु",
      "kr" : "퇴직하다"
    },
    {
      "meaning" : "लात मार्नु",
      "kr" : "툭툭 차다"
    },
    {
      "meaning" : "फ्राइ गर्नु",
      "kr" : "튀기다"
    },
    {
      "meaning" : "विशेष",
      "kr" : "특별하다"
    },
    {
      "meaning" : "विशेष गरी",
      "kr" : "특히"
    },
    {
      "meaning" : "कहिले काहिँ",
      "kr" : "틈틈이"
    },
    {
      "meaning" : "टी-शर्ट",
      "kr" : "티셔츠"
    }
  ]
}