{
  "Dic": [
    {
      "uz": "basket",
      "kr": "바구니"
    },
    {
      "uz": "to exchange",
      "kr": "바꾸다(교환하다)"
    },
    {
      "uz": "banana",
      "kr": "바나나"
    },
    {
      "uz": "netting needle",
      "kr": "바늘대"
    },
    {
      "uz": "sea",
      "kr": "바다"
    },
    {
      "uz": "beach",
      "kr": "바닷가"
    },
    {
      "uz": "to be windy",
      "kr": "바람이 불다"
    },
    {
      "uz": "immediately",
      "kr": "바로바로"
    },
    {
      "uz": "busy",
      "kr": "바쁘다"
    },
    {
      "uz": "pants",
      "kr": "바지"
    },
    {
      "uz": "to drive a nail/to drive a screw",
      "kr": "박다"
    },
    {
      "uz": "to look around a museum",
      "kr": "박물관을 관람하다"
    },
    {
      "uz": "out",
      "kr": "밖"
    },
    {
      "uz": "classmate",
      "kr": "반 친구"
    },
    {
      "uz": "to talk down",
      "kr": "반말을 하다"
    },
    {
      "uz": "side dish",
      "kr": "반찬"
    },
    {
      "uz": "band-aids",
      "kr": "반창고"
    },
    {
      "uz": "feet",
      "kr": "발"
    },
    {
      "uz": "to be issued",
      "kr": "발급 받다"
    },
    {
      "uz": "to apply for an issuance",
      "kr": "발급을 신청하다"
    },
    {
      "uz": "ankles",
      "kr": "발목"
    },
    {
      "uz": "to sprain one’s ankle",
      "kr": "발목을 삐다"
    },
    {
      "uz": "to get a foot struck",
      "kr": "발이 깔리다"
    },
    {
      "uz": "night",
      "kr": "밤"
    },
    {
      "uz": "rice",
      "kr": "밥"
    },
    {
      "uz": "to hold a rice bowl to eat",
      "kr": "밥그릇을 들고 먹다"
    },
    {
      "uz": "rice cooker",
      "kr": "밥솥"
    },
    {
      "uz": "to put the spoon in a rice bowl",
      "kr": "밥에 숟가락을 꽂다"
    },
    {
      "uz": "to cook rice",
      "kr": "밥을 하다(짓다)"
    },
    {
      "uz": "rope",
      "kr": "밧줄"
    },
    {
      "uz": "room",
      "kr": "방"
    },
    {
      "uz": "Bangladesh",
      "kr": "방글라데시"
    },
    {
      "uz": "to visit",
      "kr": "방문을 하다"
    },
    {
      "uz": "Warning: radioactive",
      "kr": "방사선 물질 경고"
    },
    {
      "uz": "inattentive",
      "kr": "방심하다"
    },
    {
      "uz": "directions",
      "kr": "방향"
    },
    {
      "uz": "field",
      "kr": "밭"
    },
    {
      "uz": "stomach/ship",
      "kr": "배"
    },
    {
      "uz": "to get stuffed with food",
      "kr": "배 터지게 먹다"
    },
    {
      "uz": "to deliver",
      "kr": "배달하다"
    },
    {
      "uz": "to play badminton",
      "kr": "배드민턴을 치다"
    },
    {
      "uz": "considerate",
      "kr": "배려하다"
    },
    {
      "uz": "faces and urine",
      "kr": "배설물"
    },
    {
      "uz": "to see someone off",
      "kr": "배웅하다"
    },
    {
      "uz": "chinese cabbage",
      "kr": "배추"
    },
    {
      "uz": "to have an upset stomach",
      "kr": "배탈이 나다"
    },
    {
      "uz": "one hundredth day",
      "kr": "백일"
    },
    {
      "uz": "department store",
      "kr": "백화점"
    },
    {
      "uz": "plastic bandages",
      "kr": "밴드"
    },
    {
      "uz": "to put on a band-aid on",
      "kr": "밴드를 붙이다"
    },
    {
      "uz": "strapping machine",
      "kr": "밴딩기"
    },
    {
      "uz": "to throw away",
      "kr": "버리다"
    },
    {
      "uz": "bus stop",
      "kr": "버스 정류장"
    },
    {
      "uz": "bus terminal",
      "kr": "버스터미널"
    },
    {
      "uz": "to take a number",
      "kr": "번호표를 뽑다"
    },
    {
      "uz": "to pay a fine",
      "kr": "벌금을 내다"
    },
    {
      "uz": "to save (something)",
      "kr": "벌다"
    },
    {
      "uz": "to get rid of worms",
      "kr": "벌레를 잡다"
    },
    {
      "uz": "legal training",
      "kr": "법률 교육"
    },
    {
      "uz": "by law",
      "kr": "법적으로"
    },
    {
      "uz": "standard working hours",
      "kr": "법정 근로 시간"
    },
    {
      "uz": "statutory vacation",
      "kr": "법정 휴일"
    },
    {
      "uz": "pillow",
      "kr": "베개"
    },
    {
      "uz": "Vietnam",
      "kr": "베트남"
    },
    {
      "uz": "rice",
      "kr": "벼"
    },
    {
      "uz": "brick",
      "kr": "벽돌"
    },
    {
      "uz": "possible number of changes",
      "kr": "변경 가능 횟수"
    },
    {
      "uz": "star",
      "kr": "별"
    },
    {
      "uz": "to pay separately",
      "kr": "별도로 지급하다"
    },
    {
      "uz": "sick leave",
      "kr": "병가"
    },
    {
      "uz": "period of sick leave",
      "kr": "병가 기간"
    },
    {
      "uz": "causes of sick leave",
      "kr": "병가 사유"
    },
    {
      "uz": "medical bills",
      "kr": "병원비"
    },
    {
      "uz": "illness",
      "kr": "병환"
    },
    {
      "uz": "(public) health center",
      "kr": "보건소"
    },
    {
      "uz": "to report",
      "kr": "보고하다"
    },
    {
      "uz": "to store",
      "kr": "보관하다"
    },
    {
      "uz": "to see the full moon",
      "kr": "보름달을 보다"
    },
    {
      "uz": "barley",
      "kr": "보리"
    },
    {
      "uz": "to receive settlement funds",
      "kr": "보상을 받다"
    },
    {
      "uz": "to repair",
      "kr": "보수하다"
    },
    {
      "uz": "safety goggles",
      "kr": "보안경"
    },
    {
      "uz": "safety mask",
      "kr": "보안면"
    },
    {
      "uz": "usually",
      "kr": "보통"
    },
    {
      "uz": "No pedestrians",
      "kr": "보행금지"
    },
    {
      "uz": "to pay out insurance claims",
      "kr": "보험금을 지급하다"
    },
    {
      "uz": "to file an insurance claim",
      "kr": "보험금을 청구하다"
    },
    {
      "uz": "to receive insurance payouts",
      "kr": "보험금을 타다"
    },
    {
      "uz": "to have expenses reimbursed",
      "kr": "보험금을 환급 받다"
    },
    {
      "uz": "to pay insurance premium",
      "kr": "보험료를 내다"
    },
    {
      "uz": "to enroll in insurance plans",
      "kr": "보험에 가입하다"
    },
    {
      "uz": "safety gear",
      "kr": "보호구"
    },
    {
      "uz": "protective clothing",
      "kr": "보호복"
    },
    {
      "uz": "three hottest sultry days of summer",
      "kr": "복날"
    },
    {
      "uz": "hallway",
      "kr": "복도"
    },
    {
      "uz": "to review",
      "kr": "복습하다"
    },
    {
      "uz": "complicated/crowded",
      "kr": "복잡하다"
    },
    {
      "uz": "to stir fry",
      "kr": "볶다"
    },
    {
      "uz": "to play bowling",
      "kr": "볼링을 치다"
    },
    {
      "uz": "bolt",
      "kr": "볼트"
    },
    {
      "uz": "pen",
      "kr": "볼펜"
    },
    {
      "uz": "spring",
      "kr": "봄"
    },
    {
      "uz": "to burden / to bear",
      "kr": "부담하다"
    },
    {
      "uz": "to collide",
      "kr": "부딪히다"
    },
    {
      "uz": "crash disaster",
      "kr": "부딪힘 재해"
    },
    {
      "uz": "to call out",
      "kr": "부르다"
    },
    {
      "uz": "buoy",
      "kr": "부자"
    },
    {
      "uz": "diligent",
      "kr": "부지런하다"
    },
    {
      "uz": "buoy",
      "kr": "부표"
    },
    {
      "uz": "one’s junior",
      "kr": "부하"
    },
    {
      "uz": "feces and urine",
      "kr": "분뇨"
    },
    {
      "uz": "to categorize to classify",
      "kr": "분류하다"
    },
    {
      "uz": "to sort out",
      "kr": "분리하다"
    },
    {
      "uz": "to have a bad atmosphere",
      "kr": "분위기가 나쁘다"
    },
    {
      "uz": "to have a good atmosphere",
      "kr": "분위기가 좋다"
    },
    {
      "uz": "fire",
      "kr": "불"
    },
    {
      "uz": "impossible",
      "kr": "불가능하다"
    },
    {
      "uz": "Buddhist scriptures",
      "kr": "불경"
    },
    {
      "uz": "Bulgogi",
      "kr": "불고기"
    },
    {
      "uz": "Buddhism",
      "kr": "불교"
    },
    {
      "uz": "to spark",
      "kr": "불꽃이 튀다"
    },
    {
      "uz": "to get bloat",
      "kr": "불룩해지다"
    },
    {
      "uz": "illegal stay",
      "kr": "불법 체류"
    },
    {
      "uz": "a fire breaks out",
      "kr": "불이 나다"
    },
    {
      "uz": "to disadvantage",
      "kr": "불이익을 주다"
    },
    {
      "uz": "to make offerings",
      "kr": "불전/헌금을 내다"
    },
    {
      "uz": "displeasure",
      "kr": "불쾌감"
    },
    {
      "uz": "unpleasant",
      "kr": "불쾌하다"
    },
    {
      "uz": "uncomfortable",
      "kr": "불편하다"
    },
    {
      "uz": "to be disqualified / to fail",
      "kr": "불합격하다"
    },
    {
      "uz": "fabric bandages",
      "kr": "붕대"
    },
    {
      "uz": "to wrap a bandage",
      "kr": "붕대를 감다"
    },
    {
      "uz": "to stick",
      "kr": "붙이다"
    },
    {
      "uz": "blog",
      "kr": "블로그"
    },
    {
      "uz": "to rain",
      "kr": "비가 오다"
    },
    {
      "uz": "scaffolding",
      "kr": "비계"
    },
    {
      "uz": "soap",
      "kr": "비누"
    },
    {
      "uz": "vinyl straps",
      "kr": "비닐 끈"
    },
    {
      "uz": "(vinyl) greenhouse",
      "kr": "비닐하우스"
    },
    {
      "uz": "to fertilize",
      "kr": "비료를 뿌리다"
    },
    {
      "uz": "password",
      "kr": "비밀번호"
    },
    {
      "uz": "emergency contact list",
      "kr": "비상 연락처"
    },
    {
      "uz": "assistant",
      "kr": "비서"
    },
    {
      "uz": "similar",
      "kr": "비슷하다"
    },
    {
      "uz": "expensive",
      "kr": "비싸다"
    },
    {
      "uz": "Visa",
      "kr": "비자"
    },
    {
      "uz": "plane",
      "kr": "비행기"
    },
    {
      "uz": "brush",
      "kr": "빗"
    },
    {
      "uz": "broom",
      "kr": "빗자루"
    },
    {
      "uz": "early",
      "kr": "빠르다(이르다)"
    },
    {
      "uz": "to excuse oneself from",
      "kr": "빠지다"
    },
    {
      "uz": "to bring in laundry",
      "kr": "빨래를 걷다"
    },
    {
      "uz": "to hang out wash",
      "kr": "빨래를 널다"
    },
    {
      "uz": "to do laundry",
      "kr": "빨래를 하다"
    },
    {
      "uz": "to be pulled into",
      "kr": "빨려 들어가다"
    },
    {
      "uz": "bread",
      "kr": "빵"
    },
    {
      "uz": "to pull out",
      "kr": "빼다"
    },
    {
      "uz": "to be selected",
      "kr": "뽑히다"
    },
    {
      "uz": "root",
      "kr": "뿌리"
    }
  ]
}